blackcraft_exporter/__init__.py
blackcraft_exporter/__main__.py
blackcraft_exporter/config.py
blackcraft_exporter/constants.py
blackcraft_exporter/context.py
blackcraft_exporter/dto.py
blackcraft_exporter/logger.py
blackcraft_exporter/main.py
blackcraft_exporter/mc.py
blackcraft_exporter/probes.py
blackcraft_exporter/server.py
blackcraft_exporter/utils.py
blackcraft_exporter-0.1.7.dist-info/LICENSE
blackcraft_exporter-0.1.7.dist-info/METADATA
blackcraft_exporter-0.1.7.dist-info/WHEEL
blackcraft_exporter-0.1.7.dist-info/entry_points.txt
blackcraft_exporter-0.1.7.dist-info/RECORD
