Metadata-Version: 2.3
Name: blackcraft_exporter
Version: 0.1.7
Summary: A blackbox_exporter-like prober for Minecraft
License: GPL-3.0-only
Keywords: minecraft,prometheus,prometheus-exporter
Author: Fallen_Breath
Requires-Python: >=3.11,<4.0
Classifier: License :: OSI Approved :: GNU General Public License v3 (GPLv3)
Classifier: Programming Language :: Python :: 3
Classifier: Programming Language :: Python :: 3.11
Classifier: Programming Language :: Python :: 3.12
Classifier: Programming Language :: Python :: 3.13
Requires-Dist: dnspython (>=2.7.0,<3.0.0)
Requires-Dist: fastapi (>=0.115.8,<0.116.0)
Requires-Dist: mcstatus (>=11.1.1,<12.0.0)
Requires-Dist: prometheus-client (>=0.21.1,<0.22.0)
Requires-Dist: pydantic (>=2.10.6,<3.0.0)
Requires-Dist: pydantic-settings (>=2.7.1,<3.0.0)
Requires-Dist: python-socks[asyncio] (>=2.7.1,<3.0.0)
Requires-Dist: uvicorn[standard] (>=0.34.0,<0.35.0)
Project-URL: Repository, https://github.com/Fallen-Breath/blackcraft_exporter
